shipitchile/__init__.py
shipitchile/exceptions.py
shipitchile/quotation_request.py
shipitchile/shipit.py
shipitchile/shipping_request.py
shipitchile-1.dist-info/DESCRIPTION.rst
shipitchile-1.dist-info/METADATA
shipitchile-1.dist-info/RECORD
shipitchile-1.dist-info/WHEEL
shipitchile-1.dist-info/metadata.json
shipitchile-1.dist-info/top_level.txt
