Metadata-Version: 2.0
Name: shipitchile
Version: 1
Summary: Library that allows integration with the Shipit API. http://shipit.cl/
Home-page: https://github.com/jeffersonlizar/shipitchile
Author: Jefferson Lizarzabal
Author-email: dvjefferson@gmail.com
License: UNKNOWN
Project-URL: Bug Reports, https://github.com/jeffersonlizar/shipitchile/issues
Project-URL: Funding, https://donate.pypi.org
Project-URL: Say Thanks!, https://saythanks.io/to/jeffersonlizar
Project-URL: Source, https://github.com/jeffersonlizar/shipitchile
Requires-Dist: requests
Provides-Extra: dev
Requires-Dist: check-manifest; extra == 'dev'
Provides-Extra: test
Requires-Dist: coverage; extra == 'test'
Requires-Dist: pytest; extra == 'test'
